examples/Example1.py
examples/__init__.py
src/DisplControlSubStepping.py
src/LoadControlSubStepping.py
src/__init__.py
OpenSeesPySubStepping-0.1.2.1.dist-info/LICENSE
OpenSeesPySubStepping-0.1.2.1.dist-info/METADATA
OpenSeesPySubStepping-0.1.2.1.dist-info/WHEEL
OpenSeesPySubStepping-0.1.2.1.dist-info/top_level.txt
OpenSeesPySubStepping-0.1.2.1.dist-info/RECORD
