Metadata-Version: 2.1
Name: OpenSeesPySubStepping
Version: 0.1.2.1
Summary: Substepping method for LoadControl and Displacement Control Analysis
Home-page: UNKNOWN
Author: Konstantinos Mixios
Author-email: k.mixios@gmail.com
License: UNKNOWN
Platform: UNKNOWN
Classifier: Programming Language :: Python :: 3
Classifier: License :: OSI Approved :: MIT License
Classifier: Operating System :: OS Independent
Requires-Python: >=3.7.9
